django_textflow-0.1.3.dist-info/DESCRIPTION.rst
django_textflow-0.1.3.dist-info/METADATA
django_textflow-0.1.3.dist-info/RECORD
django_textflow-0.1.3.dist-info/WHEEL
django_textflow-0.1.3.dist-info/metadata.json
django_textflow-0.1.3.dist-info/top_level.txt
textflow/__init__.py
textflow/admin.py
textflow/models.py
textflow/translation.py
textflow/migrations/0001_initial.py
textflow/migrations/__init__.py
textflow/static/javascripts/jquery.textflow.min.js
textflow/static/stylesheets/textflow.min.css
textflow/templates/textflow.html
textflow/templatetags/__init__.py
textflow/templatetags/textflow.py
